{
  "meeting_live": [
    {
      "type": "turn",
      "round": 1,
      "turn": 1,
      "speaker": "Alice",
      "content": "{\"cycle\": 1, \"diverge\": [{\"hypothesis\": \"テーマ再掲: E2E旧フロー\\n最近の覚書:\\n- 個性プロファイル(ASSERTIVE): 意思決定を急ぎ、明確な行動を求める推進役。\", \"assumptions\": []}], \"learn\": [], \"converge\": [{\"commit\": \"改善案: 手順・安全・得点方法を明記\", \"reason\": \"\"}], \"next_goal\": \"\"}",
      "phase": {
        "id": 0,
        "turn": 1,
        "kind": "discussion",
        "base": 0
      }
    },
    {
      "type": "summary",
      "round": 1,
      "summary": "- 差分: 改善案: 手順・安全・得点方法を明記",
      "phase": {
        "id": 0,
        "turn": 1,
        "kind": "discussion",
        "base": 0
      }
    },
    {
      "type": "turn",
      "round": 2,
      "turn": 2,
      "speaker": "Bob",
      "content": "{\"cycle\": 2, \"diverge\": [{\"hypothesis\": \"前回の発言者: Alice\\n発言要約: 改善案: 手順・安全・得点方法を明記\\n前ラウンド要約:\\n- 差分: 改善案: 手順・安全・得点方法を明記\\nテーマ再掲: E2E旧フロー\\n最近の覚書:\\n- 個性プロファイル(EMPATHIC): 相手の感情と懸念をすくい上げ、協調的な合意形成を促す支援役。\\n- Aliceの発言: 差分: 改善案: 手順・安全・得点方法を明記\", \"assumptions\": []}], \"learn\": [{\"insight\": \"差分: 改善案: 手順・安全・得点方法を明記\", \"why\": \"\", \"links\": []}, {\"insight\": \"差分: 改善案: 手順・安全・得点方法を明記\", \"why\": \"\", \"links\": []}], \"converge\": [{\"commit\": \"改善案: 手順・安全・得点方法を明記\", \"reason\": \"\"}], \"next_goal\": \"\"}",
      "phase": {
        "id": 0,
        "turn": 2,
        "kind": "discussion",
        "base": 0
      }
    },
    {
      "type": "summary",
      "round": 2,
      "summary": "- 差分: 改善案: 手順・安全・得点方法を明記",
      "phase": {
        "id": 0,
        "turn": 2,
        "kind": "discussion",
        "base": 0
      }
    },
    {
      "type": "final",
      "final": "合意事項:\n- 空間を活かす新スポーツを実証する\n- 用具の安全確保と得点管理を両立\n残課題:\n- 動作手順の動画化で理解を補強\n直近アクション:\n- Alice が安全テストの検証案を整備\n- Bob がKPI測定の設計案を仕上げる"
    }
  ],
  "kpi": {
    "progress": 0.0,
    "diversity": 0.548,
    "decision_density": 1.0,
    "spec_coverage": 1.0
  },
  "meeting_result": {
    "topic": "E2E旧フロー",
    "precision": 4,
    "rounds": 2,
    "phase_turn_limit": 2,
    "max_phases": null,
    "phase_goal": null,
    "resolve_phase": false,
    "agents": [
      {
        "name": "Alice",
        "system": "あなたは会議参加者です。日本語で短く発言し、直前の内容に具体的に応答し、次の一手を提示してください。見出し/箇条書き/長い前置きは禁止",
        "style": "",
        "reveal_think": false,
        "memory": []
      },
      {
        "name": "Bob",
        "system": "あなたは会議参加者です。日本語で短く発言し、直前の内容に具体的に応答し、次の一手を提示してください。見出し/箇条書き/長い前置きは禁止",
        "style": "",
        "reveal_think": false,
        "memory": []
      }
    ],
    "turns": [
      {
        "speaker": "Alice",
        "content": "{\"cycle\": 1, \"diverge\": [{\"hypothesis\": \"テーマ再掲: E2E旧フロー\\n最近の覚書:\\n- 個性プロファイル(ASSERTIVE): 意思決定を急ぎ、明確な行動を求める推進役。\", \"assumptions\": []}], \"learn\": [], \"converge\": [{\"commit\": \"改善案: 手順・安全・得点方法を明記\", \"reason\": \"\"}], \"next_goal\": \"\"}",
        "meta": {}
      },
      {
        "speaker": "Bob",
        "content": "{\"cycle\": 2, \"diverge\": [{\"hypothesis\": \"前回の発言者: Alice\\n発言要約: 改善案: 手順・安全・得点方法を明記\\n前ラウンド要約:\\n- 差分: 改善案: 手順・安全・得点方法を明記\\nテーマ再掲: E2E旧フロー\\n最近の覚書:\\n- 個性プロファイル(EMPATHIC): 相手の感情と懸念をすくい上げ、協調的な合意形成を促す支援役。\\n- Aliceの発言: 差分: 改善案: 手順・安全・得点方法を明記\", \"assumptions\": []}], \"learn\": [{\"insight\": \"差分: 改善案: 手順・安全・得点方法を明記\", \"why\": \"\", \"links\": []}, {\"insight\": \"差分: 改善案: 手順・安全・得点方法を明記\", \"why\": \"\", \"links\": []}], \"converge\": [{\"commit\": \"改善案: 手順・安全・得点方法を明記\", \"reason\": \"\"}], \"next_goal\": \"\"}",
        "meta": {}
      }
    ],
    "phases": [
      {
        "id": 0,
        "start_turn": 1,
        "turn_indices": [
          1,
          2
        ],
        "unresolved_counts": [
          1,
          1
        ],
        "status": "closed",
        "turn_limit": 2,
        "turn_count": 2,
        "kind": "discussion",
        "legacy_round_base": 0
      }
    ],
    "final": "合意事項:\n- 空間を活かす新スポーツを実証する\n- 用具の安全確保と得点管理を両立\n残課題:\n- 動作手順の動画化で理解を補強\n直近アクション:\n- Alice が安全テストの検証案を整備\n- Bob がKPI測定の設計案を仕上げる",
    "kpi": {
      "progress": 0.0,
      "diversity": 0.548,
      "decision_density": 1.0,
      "spec_coverage": 1.0
    },
    "files": {
      "meeting_live_md": "meeting_live.md",
      "meeting_live_jsonl": "meeting_live.jsonl",
      "meeting_live_html": "meeting_live.html",
      "phases_jsonl": "phases.jsonl",
      "thoughts_jsonl": "thoughts.jsonl",
      "control_jsonl": "control.jsonl",
      "kpi_json": "kpi.json",
      "metrics_csv": "metrics.csv",
      "metrics_cpu_mem_png": "metrics_cpu_mem.png",
      "metrics_gpu_png": "metrics_gpu.png"
    }
  }
}
